pyfast_sqlite
