Metadata-Version: 2.1
Name: pyfast-sqlite
Version: 0.1.1
Summary: Fast_sqlite is a library to use sqlite database faster and easier.
Home-page: https://github.com/Unknow-per/Fast_sqlite-lIbrary
Author: Farbod Parkhooi
Author-email: farbod.p1390@gmail.com
Project-URL: Bug Tracker, https://github.com/Unknow-per/Fast_sqlite-lIbrary/~/issues
Classifier: Programming Language :: Python :: 3
Classifier: License :: OSI Approved :: MIT License
Classifier: Operating System :: OS Independent
Requires-Python: >=3.8
License-File: LICENSE
Requires-Dist: numpy
